grade_tracker/__init__.py
grade_tracker/__main__.py
grade_tracker/cli.py
grade_tracker-2.0.0.dist-info/LICENSE
grade_tracker-2.0.0.dist-info/METADATA
grade_tracker-2.0.0.dist-info/WHEEL
grade_tracker-2.0.0.dist-info/entry_points.txt
grade_tracker-2.0.0.dist-info/top_level.txt
grade_tracker-2.0.0.dist-info/RECORD
