Metadata-Version: 2.1
Name: grade-tracker
Version: 2.0.0
Summary: A CLI to track grades
Home-page: https://github.com/dwdwdan/grade-tracker
Author: Dan Walters
Author-email: dan.walters5@outlook.com
Requires-Python: >=3.6
License-File: LICENSE
Requires-Dist: xdg
Requires-Dist: pyyaml
